src/__init__.py
src/main.py
src/commands/__init__.py
src/commands/bundle.py
src/commands/list.py
src/commands/resolve.py
src/commands/scaffold.py
src/models/__init__.py
src/models/route.py
src/models/route_collection.py
src/resources/__init__.py
src/resources/template.html
src/utils/__init__.py
src/utils/export.py
src/utils/file_control.py
src/utils/repository.py
src/utils/resolver.py
openapi_cli_tool-0.3.0.dist-info/LICENSE
openapi_cli_tool-0.3.0.dist-info/METADATA
openapi_cli_tool-0.3.0.dist-info/WHEEL
openapi_cli_tool-0.3.0.dist-info/entry_points.txt
openapi_cli_tool-0.3.0.dist-info/top_level.txt
openapi_cli_tool-0.3.0.dist-info/RECORD
