Metadata-Version: 2.1
Name: openapi-cli-tool
Version: 0.3.0
Summary: openapi cli tool
Home-page: https://github.com/hakopako/openapi-cli-tool
Author: Ayaka Shimada
Author-email: aya.a.shimada@gmail.com
License: MIT
Platform: UNKNOWN
Requires-Dist: click (==7.0)
Requires-Dist: pyyaml (==5.1)
Requires-Dist: tabulate (==0.8.3)
